MANIFEST.in
README.rst
setup.py
bin/mdp-problog
docs/_build/html/.buildinfo
docs/_build/html/genindex.html
docs/_build/html/index.html
docs/_build/html/mdpproblog.html
docs/_build/html/objects.inv
docs/_build/html/py-modindex.html
docs/_build/html/search.html
docs/_build/html/searchindex.js
mdpproblog/__init__.py
mdpproblog/engine.py
mdpproblog/fluent.py
mdpproblog/mdp.py
mdpproblog/simulator.py
mdpproblog/value_iteration.py
mdpproblog.egg-info/PKG-INFO
mdpproblog.egg-info/SOURCES.txt
mdpproblog.egg-info/dependency_links.txt
mdpproblog.egg-info/not-zip-safe
mdpproblog.egg-info/requires.txt
mdpproblog.egg-info/top_level.txt
mdpproblog/models/sysadmin/IPPC_inst_1.pl
mdpproblog/models/sysadmin/domain.pl
mdpproblog/models/sysadmin/domain2.pl
mdpproblog/models/sysadmin/star2.pl
mdpproblog/models/sysadmin/star3.pl
mdpproblog/models/sysadmin/star4.pl
mdpproblog/models/sysadmin/star5.pl
mdpproblog/models/sysadmin/star6.pl
mdpproblog/models/sysadmin/star7.pl
mdpproblog/models/sysadmin/star8.pl
mdpproblog/models/sysadmin/star9.pl
mdpproblog/models/viralmarketing/domain1.pl
mdpproblog/models/viralmarketing/domain2.pl
mdpproblog/models/viralmarketing/domain3.pl
mdpproblog/models/viralmarketing/domain4.pl
mdpproblog/models/viralmarketing/network1.pl
mdpproblog/models/viralmarketing/network2.pl
tests/__init__.py
tests/test_engine.py
tests/test_fluent.py
tests/test_mdp.py
tests/test_value_iteration.py