Metadata-Version: 1.1
Name: mdpproblog
Version: 0.3.0
Summary: A probabilistic logic programming framework to represent and solve MDPs.
Home-page: https://github.com/thiagopbueno/mdp-problog
Author: Thiago P. Bueno
Author-email: thiago.pbueno@gmail.com
License: GNU General Public License v3.0
Keywords: planning,mdp,problog,probabilistic logic programming
Platform: UNKNOWN
Classifier: Development Status :: 3 - Alpha
Classifier: Environment :: Console
Classifier: Intended Audience :: Science/Research
Classifier: License :: OSI Approved :: GNU General Public License v3 (GPLv3)
Classifier: Natural Language :: English
Classifier: Operating System :: OS Independent
Classifier: Programming Language :: Python :: 3
Classifier: Topic :: Scientific/Engineering :: Artificial Intelligence
